[
    {
        "Title": "Lose author per",
        "Author": "Dr. Patricia Fuentes",
        "ISBN": "978-1-312-68179-8",
        "AvailableCopies": 2
    },
    {
        "Title": "Image sport man",
        "Author": "Margaret Thomas",
        "ISBN": "978-1-101-00507-1",
        "AvailableCopies": 4
    },
    {
        "Title": "Important industry",
        "Author": "Hannah Sanders",
        "ISBN": "978-1-895845-84-6",
        "AvailableCopies": 11
    },
    {
        "Title": "Wife particularly run section hot",
        "Author": "Christopher Hughes",
        "ISBN": "978-1-79906-816-7",
        "AvailableCopies": 15
    },
    {
        "Title": "Environment born player I",
        "Author": "Alexandra Rodriguez",
        "ISBN": "978-1-231-82083-4",
        "AvailableCopies": 17
    },
    {
        "Title": "World card allow executive",
        "Author": "Vernon Williams",
        "ISBN": "978-0-02-639661-5",
        "AvailableCopies": 13
    },
    {
        "Title": "Purpose imagine",
        "Author": "Travis Barnett",
        "ISBN": "978-1-66773-797-3",
        "AvailableCopies": 4
    },
    {
        "Title": "Arm cold onto",
        "Author": "James Herrera",
        "ISBN": "978-1-292-30670-4",
        "AvailableCopies": 6
    },
    {
        "Title": "Without use region consider",
        "Author": "Tim Crawford",
        "ISBN": "978-1-66449-709-2",
        "AvailableCopies": 11
    },
    {
        "Title": "Somebody either range mind",
        "Author": "Brooke Phillips",
        "ISBN": "978-1-5479-8243-1",
        "AvailableCopies": 8
    },
    {
        "Title": "Final season thought just",
        "Author": "Samantha Holmes",
        "ISBN": "978-1-4347-0474-0",
        "AvailableCopies": 5
    },
    {
        "Title": "Investment view",
        "Author": "Larry Moore",
        "ISBN": "978-1-85236-543-1",
        "AvailableCopies": 12
    },
    {
        "Title": "Buy learn especially serious",
        "Author": "Rachel Espinoza",
        "ISBN": "978-1-7377161-9-8",
        "AvailableCopies": 1
    },
    {
        "Title": "Successful trip relate treat",
        "Author": "Thomas Doyle",
        "ISBN": "978-1-942193-80-7",
        "AvailableCopies": 9
    },
    {
        "Title": "Tree operation add",
        "Author": "Darrell Perry",
        "ISBN": "978-0-934456-68-5",
        "AvailableCopies": 4
    },
    {
        "Title": "Could green without become",
        "Author": "Tyler Collins",
        "ISBN": "978-0-07-098829-3",
        "AvailableCopies": 6
    },
    {
        "Title": "Bring scene rule him",
        "Author": "Samuel West",
        "ISBN": "978-0-688-61226-9",
        "AvailableCopies": 14
    },
    {
        "Title": "Near happen them lose",
        "Author": "Robert Moon",
        "ISBN": "978-0-337-18365-2",
        "AvailableCopies": 19
    },
    {
        "Title": "Near light bill benefit",
        "Author": "Jeremy Webb",
        "ISBN": "978-0-612-20712-7",
        "AvailableCopies": 10
    },
    {
        "Title": "If opportunity and",
        "Author": "Joshua Orozco",
        "ISBN": "978-1-326-29693-3",
        "AvailableCopies": 17
    },
    {
        "Title": "Down everything shake",
        "Author": "Douglas Graham",
        "ISBN": "978-0-923528-24-9",
        "AvailableCopies": 4
    },
    {
        "Title": "Start teach contain",
        "Author": "Edward Patterson",
        "ISBN": "978-0-01-314973-6",
        "AvailableCopies": 2
    },
    {
        "Title": "Make light reason college",
        "Author": "Adam Wilson",
        "ISBN": "978-0-337-22398-3",
        "AvailableCopies": 7
    },
    {
        "Title": "Anyone since officer",
        "Author": "Donna Myers",
        "ISBN": "978-1-5286-8740-9",
        "AvailableCopies": 7
    },
    {
        "Title": "Hand another write matter first",
        "Author": "Martin Thomas",
        "ISBN": "978-0-05-116817-1",
        "AvailableCopies": 16
    },
    {
        "Title": "Adult car spring watch",
        "Author": "Michelle Smith",
        "ISBN": "978-1-07-135638-8",
        "AvailableCopies": 9
    },
    {
        "Title": "Say smile product",
        "Author": "Nicholas Porter",
        "ISBN": "978-1-64692-384-7",
        "AvailableCopies": 11
    },
    {
        "Title": "Health soldier young",
        "Author": "Daniel Grant",
        "ISBN": "978-1-58587-191-9",
        "AvailableCopies": 19
    },
    {
        "Title": "Rest gun join successful",
        "Author": "Paula Lucas",
        "ISBN": "978-0-463-41651-8",
        "AvailableCopies": 1
    },
    {
        "Title": "Capital everyone",
        "Author": "Elizabeth Berg",
        "ISBN": "978-0-9821134-8-6",
        "AvailableCopies": 8
    },
    {
        "Title": "Foreign general show",
        "Author": "Thomas Hoffman",
        "ISBN": "978-1-55252-285-1",
        "AvailableCopies": 10
    },
    {
        "Title": "Current resource",
        "Author": "Mr. Samuel Schmidt",
        "ISBN": "978-1-07-594173-3",
        "AvailableCopies": 10
    },
    {
        "Title": "Fine course",
        "Author": "Philip Kelly",
        "ISBN": "978-0-06-076015-1",
        "AvailableCopies": 17
    },
    {
        "Title": "North medical tax",
        "Author": "David Ryan",
        "ISBN": "978-0-926041-22-6",
        "AvailableCopies": 7
    },
    {
        "Title": "Protect account sort involve",
        "Author": "Jacob West",
        "ISBN": "978-0-506-03494-5",
        "AvailableCopies": 7
    },
    {
        "Title": "Head listen discover fill baby",
        "Author": "Becky Shepard",
        "ISBN": "978-0-688-88613-4",
        "AvailableCopies": 7
    },
    {
        "Title": "Decision write cultural",
        "Author": "Kim Marsh",
        "ISBN": "978-1-57302-787-8",
        "AvailableCopies": 19
    },
    {
        "Title": "Worry help believe contain try",
        "Author": "Bonnie Steele",
        "ISBN": "978-0-15-376409-7",
        "AvailableCopies": 15
    },
    {
        "Title": "Writer not yourself easy for",
        "Author": "Christopher Osborn",
        "ISBN": "978-1-74525-644-0",
        "AvailableCopies": 9
    },
    {
        "Title": "Us young opportunity",
        "Author": "Gary Williams",
        "ISBN": "978-0-315-61071-2",
        "AvailableCopies": 9
    },
    {
        "Title": "Experience center thing yourself game",
        "Author": "Linda Montgomery",
        "ISBN": "978-0-19-405727-1",
        "AvailableCopies": 5
    },
    {
        "Title": "Simple education population",
        "Author": "Michelle Allen",
        "ISBN": "978-1-339-20948-7",
        "AvailableCopies": 9
    },
    {
        "Title": "Free store into executive wife",
        "Author": "Tanya Smith",
        "ISBN": "978-1-129-99813-3",
        "AvailableCopies": 19
    },
    {
        "Title": "Boy become option ability",
        "Author": "Leon Smith DDS",
        "ISBN": "978-1-128-99818-9",
        "AvailableCopies": 3
    },
    {
        "Title": "Wrong low organization bag",
        "Author": "Cindy Pugh",
        "ISBN": "978-0-9827856-1-4",
        "AvailableCopies": 8
    },
    {
        "Title": "Nation expect along",
        "Author": "Noah Evans",
        "ISBN": "978-0-8041-5181-8",
        "AvailableCopies": 20
    },
    {
        "Title": "Four consumer put difference",
        "Author": "Gerald Bryant",
        "ISBN": "978-1-154-61599-9",
        "AvailableCopies": 7
    },
    {
        "Title": "Site test southern unit however",
        "Author": "Emily Jones",
        "ISBN": "978-1-5382-2745-9",
        "AvailableCopies": 10
    },
    {
        "Title": "Drop might manage federal set",
        "Author": "Yvonne Black",
        "ISBN": "978-0-9971818-8-3",
        "AvailableCopies": 20
    },
    {
        "Title": "Person system brother",
        "Author": "Kathleen Khan",
        "ISBN": "978-0-7500-3861-4",
        "AvailableCopies": 14
    },
    {
        "Title": "Why through them hold",
        "Author": "Jonathan Randall",
        "ISBN": "978-0-8420-5481-2",
        "AvailableCopies": 12
    },
    {
        "Title": "Win assume not wind daughter",
        "Author": "Wesley Archer",
        "ISBN": "978-1-4742-5915-6",
        "AvailableCopies": 1
    },
    {
        "Title": "Support some among",
        "Author": "Michelle Lopez",
        "ISBN": "978-1-327-11231-7",
        "AvailableCopies": 7
    },
    {
        "Title": "Prepare reason physical newspaper",
        "Author": "Christine Mcmahon",
        "ISBN": "978-0-02-918151-5",
        "AvailableCopies": 9
    },
    {
        "Title": "Measure song five",
        "Author": "Bruce Liu",
        "ISBN": "978-1-83909-725-6",
        "AvailableCopies": 14
    },
    {
        "Title": "Away food media different",
        "Author": "Ashley Ortiz",
        "ISBN": "978-1-80413-915-8",
        "AvailableCopies": 15
    },
    {
        "Title": "Movie wife",
        "Author": "Philip Smith",
        "ISBN": "978-0-02-755039-9",
        "AvailableCopies": 11
    },
    {
        "Title": "So yet be include accept",
        "Author": "Christopher Peters",
        "ISBN": "978-1-63732-760-9",
        "AvailableCopies": 11
    },
    {
        "Title": "Fine chair I our face",
        "Author": "Debra Alvarez",
        "ISBN": "978-0-03-625680-0",
        "AvailableCopies": 18
    },
    {
        "Title": "Year yeah side",
        "Author": "Adam Jones",
        "ISBN": "978-0-386-09965-2",
        "AvailableCopies": 14
    },
    {
        "Title": "Seek daughter nothing",
        "Author": "Adrian Zimmerman",
        "ISBN": "978-1-249-12910-3",
        "AvailableCopies": 9
    },
    {
        "Title": "Evidence loss brother area ahead",
        "Author": "Tammy Edwards",
        "ISBN": "978-0-264-03216-0",
        "AvailableCopies": 12
    },
    {
        "Title": "Sometimes support answer",
        "Author": "Lauren Johnson",
        "ISBN": "978-0-307-16384-4",
        "AvailableCopies": 9
    },
    {
        "Title": "Section front system",
        "Author": "Robin Tucker",
        "ISBN": "978-1-375-38113-0",
        "AvailableCopies": 15
    },
    {
        "Title": "For feel all",
        "Author": "Sylvia Trujillo",
        "ISBN": "978-0-923883-39-3",
        "AvailableCopies": 11
    },
    {
        "Title": "These affect understand hour",
        "Author": "Jennifer Hughes MD",
        "ISBN": "978-1-02-986858-1",
        "AvailableCopies": 6
    },
    {
        "Title": "Religious huge against fine",
        "Author": "Chelsea Stewart",
        "ISBN": "978-0-244-44756-4",
        "AvailableCopies": 1
    },
    {
        "Title": "Base late staff",
        "Author": "Jeff Ortiz",
        "ISBN": "978-1-07-432875-7",
        "AvailableCopies": 1
    },
    {
        "Title": "Determine too research large",
        "Author": "Juan Ferrell",
        "ISBN": "978-1-320-44897-0",
        "AvailableCopies": 18
    },
    {
        "Title": "Behavior past",
        "Author": "Catherine Brown",
        "ISBN": "978-1-5078-4494-6",
        "AvailableCopies": 12
    },
    {
        "Title": "Least matter marriage figure I",
        "Author": "Rodney Stokes",
        "ISBN": "978-1-263-66959-3",
        "AvailableCopies": 19
    },
    {
        "Title": "Field figure option customer imagine",
        "Author": "Charles Harrison",
        "ISBN": "978-1-01-085311-4",
        "AvailableCopies": 14
    },
    {
        "Title": "Himself fight hot",
        "Author": "Benjamin Brown",
        "ISBN": "978-0-9912444-5-4",
        "AvailableCopies": 10
    },
    {
        "Title": "Door hope",
        "Author": "Julie Jackson",
        "ISBN": "978-0-639-94854-6",
        "AvailableCopies": 9
    },
    {
        "Title": "Fear perhaps through increase family",
        "Author": "Mr. Timothy Chan",
        "ISBN": "978-1-236-25910-3",
        "AvailableCopies": 8
    },
    {
        "Title": "Along hot significant own four",
        "Author": "Patrick Jensen",
        "ISBN": "978-1-59483-612-1",
        "AvailableCopies": 8
    },
    {
        "Title": "Several soon",
        "Author": "Jessica Lewis",
        "ISBN": "978-1-83925-753-7",
        "AvailableCopies": 15
    },
    {
        "Title": "Continue those article",
        "Author": "Jennifer Ball",
        "ISBN": "978-0-929707-44-0",
        "AvailableCopies": 13
    },
    {
        "Title": "Reason respond also",
        "Author": "Sara Cook",
        "ISBN": "978-0-89039-003-0",
        "AvailableCopies": 17
    },
    {
        "Title": "Control direction",
        "Author": "Leah Collins",
        "ISBN": "978-0-547-76809-0",
        "AvailableCopies": 10
    },
    {
        "Title": "Skill officer gun",
        "Author": "Daniel Flowers",
        "ISBN": "978-1-998712-87-8",
        "AvailableCopies": 18
    },
    {
        "Title": "Figure specific range network",
        "Author": "Joseph Mitchell",
        "ISBN": "978-0-08-539328-0",
        "AvailableCopies": 3
    },
    {
        "Title": "Care ball",
        "Author": "Robert Gutierrez",
        "ISBN": "978-1-179-21320-0",
        "AvailableCopies": 4
    },
    {
        "Title": "Risk easy create",
        "Author": "Joshua Beltran",
        "ISBN": "978-1-64965-328-4",
        "AvailableCopies": 13
    },
    {
        "Title": "Model second",
        "Author": "William Donaldson",
        "ISBN": "978-1-66314-615-1",
        "AvailableCopies": 16
    },
    {
        "Title": "Agree than",
        "Author": "Kathleen Kennedy",
        "ISBN": "978-0-86904-397-4",
        "AvailableCopies": 20
    },
    {
        "Title": "Country kind get",
        "Author": "Ashley Simmons",
        "ISBN": "978-0-649-47111-9",
        "AvailableCopies": 4
    },
    {
        "Title": "Dinner couple president",
        "Author": "Tracy Roach",
        "ISBN": "978-0-219-09380-2",
        "AvailableCopies": 6
    },
    {
        "Title": "From walk process",
        "Author": "Marissa Perry",
        "ISBN": "978-1-301-21146-3",
        "AvailableCopies": 18
    },
    {
        "Title": "Themselves avoid often",
        "Author": "Shannon Stephenson",
        "ISBN": "978-1-06-843099-2",
        "AvailableCopies": 18
    },
    {
        "Title": "Notice church stay movement test",
        "Author": "William Hall",
        "ISBN": "978-0-206-05414-4",
        "AvailableCopies": 5
    },
    {
        "Title": "Student thank will direction",
        "Author": "Anthony Leon",
        "ISBN": "978-0-16-643132-0",
        "AvailableCopies": 7
    },
    {
        "Title": "Especially write cup necessary",
        "Author": "Cassandra Davis",
        "ISBN": "978-0-8050-6359-2",
        "AvailableCopies": 18
    },
    {
        "Title": "History particularly door phone effort",
        "Author": "Aaron Reed",
        "ISBN": "978-0-913111-66-6",
        "AvailableCopies": 7
    },
    {
        "Title": "Past authority citizen act",
        "Author": "Tony Stuart",
        "ISBN": "978-0-9619215-9-0",
        "AvailableCopies": 14
    },
    {
        "Title": "Black force",
        "Author": "Darren Blair",
        "ISBN": "978-1-219-45117-3",
        "AvailableCopies": 15
    },
    {
        "Title": "Scene along",
        "Author": "Christine Wu",
        "ISBN": "978-0-15-587425-1",
        "AvailableCopies": 15
    },
    {
        "Title": "Happen experience respond customer",
        "Author": "Melissa Miller",
        "ISBN": "978-1-70092-022-5",
        "AvailableCopies": 18
    },
    {
        "Title": "History practice agree",
        "Author": "Rhonda Sanchez",
        "ISBN": "978-0-396-15920-9",
        "AvailableCopies": 20
    },
    {
        "Title": "Try degree can",
        "Author": "Brandon Sampson",
        "ISBN": "978-0-09-349028-5",
        "AvailableCopies": 12
    }
]